openwillis/voice/__init__.py
openwillis/voice/acoustic.py
openwillis/voice/speech_phonation.py
openwillis/voice/speech_preprocess.py
openwillis/voice/commons/__init__.py
openwillis/voice/commons/common.py
openwillis/voice/commons/common_separation.py
openwillis/voice/config/acoustic.json
openwillis/voice/util/__init__.py
openwillis/voice/util/acoustic_util.py
openwillis/voice/util/disvoice_util.py
openwillis/voice/util/phonation_util.py
openwillis/voice/util/praat_tremor/vocal_tremor.praat
openwillis/voice/util/praat_tremor/procedures/amptrem.praat
openwillis/voice/util/praat_tremor/procedures/coninout.praat
openwillis/voice/util/praat_tremor/procedures/freqtrem.praat
openwillis/voice/util/praat_tremor/procedures/readPitchOb.praat
openwillis/voice/util/praat_tremor/procedures/tremHNR.praat
openwillis/voice/util/praat_tremor/procedures/tremIntIndex.praat
openwillis/voice/util/praat_tremor/procedures/tremProdSum.praat
openwillis_voice-1.1.0.dist-info/METADATA
openwillis_voice-1.1.0.dist-info/WHEEL
openwillis_voice-1.1.0.dist-info/top_level.txt
openwillis_voice-1.1.0.dist-info/RECORD
