Metadata-Version: 2.4
Name: openwillis-voice
Version: 1.1.0
Summary: digital health measurement
Home-page: https://github.com/bklynhlth/openwillis
Author: bklynhlth
Author-email: admin@bklynhlth.com
License: Apache
Requires-Python: >=3.9, <3.13
Requires-Dist: pandas==2.2.3
Requires-Dist: praat-parselmouth==0.4.5
Requires-Dist: pydub==0.25.1
Requires-Dist: scipy==1.11.4
Requires-Dist: disvoice==0.1.8
Requires-Dist: librosa==0.10.2.post1
Requires-Dist: numpy<1.28.0,>=1.23.5
Dynamic: author
Dynamic: author-email
Dynamic: description-content-type
Dynamic: home-page
Dynamic: license
Dynamic: requires-dist
Dynamic: requires-python
Dynamic: summary
